MalePedigreeToolbox/__init__.py
MalePedigreeToolbox/distances.py
MalePedigreeToolbox/infer_pedigree_mutations.py
MalePedigreeToolbox/main.py
MalePedigreeToolbox/mutation_diff.py
MalePedigreeToolbox/predict_pedigrees.py
MalePedigreeToolbox/run_it_all.py
MalePedigreeToolbox/thread_termination.py
MalePedigreeToolbox/utility.py
MalePedigreeToolbox/generational_distance_prediction/__init__.py
MalePedigreeToolbox/generational_distance_prediction/classifier_predict.py
MalePedigreeToolbox/generational_distance_prediction/make_models.py
MalePedigreeToolbox/generational_distance_prediction/simulate_mutations.py
MalePedigreeToolbox/generational_distance_prediction/models/PPY23_RMplex_model.joblib
MalePedigreeToolbox/generational_distance_prediction/models/PPY23_model.joblib
MalePedigreeToolbox/generational_distance_prediction/models/RMplex_model.joblib
MalePedigreeToolbox/generational_distance_prediction/models/YFP_RMplex_model.joblib
MalePedigreeToolbox/generational_distance_prediction/models/YFP_model.joblib
MalePedigreeToolbox/generational_distance_prediction/models/YForgen_RMplex_model.joblib
MalePedigreeToolbox/generational_distance_prediction/models/YForgen_model.joblib
MalePedigreeToolbox/gui/__init__.py
MalePedigreeToolbox/gui/all_gui.py
MalePedigreeToolbox/gui/distance_gui.py
MalePedigreeToolbox/gui/gui_constants.py
MalePedigreeToolbox/gui/gui_parts.py
MalePedigreeToolbox/gui/infer_pedigree_mutations_gui.py
MalePedigreeToolbox/gui/main_gui.py
MalePedigreeToolbox/gui/mutation_differentiation_gui.py
MalePedigreeToolbox/gui/predict_gui.py
MalePedigreeToolbox/gui/predict_pedigrees_gui.py
MalePedigreeToolbox/tests/__init__.py
MalePedigreeToolbox/tests/test_distances.py
MalePedigreeToolbox/tests/test_integration.py
MalePedigreeToolbox/tests/test_mutation_diff.py
MalePedigreeToolbox/tests/testing_utility.py
male_pedigree_toolbox-1.0.3.dist-info/METADATA
male_pedigree_toolbox-1.0.3.dist-info/WHEEL
male_pedigree_toolbox-1.0.3.dist-info/entry_points.txt
male_pedigree_toolbox-1.0.3.dist-info/top_level.txt
male_pedigree_toolbox-1.0.3.dist-info/RECORD
