Metadata-Version: 2.1
Name: male-pedigree-toolbox
Version: 1.0.3
Summary: tools for getting information from pedigress
Home-page: https://github.com/genid/MalePedigreeToolbox.git
Author: Bram van Wersch and Diego Montiel Gonzalez
Author-email: b.vanwersch@erasmusmc.nl
License: MIT
Platform: UNKNOWN
Classifier: Programming Language :: Python :: 3
Classifier: Programming Language :: Python :: 3.6
Classifier: License :: OSI Approved :: MIT License
Classifier: Operating System :: OS Independent
Classifier: Intended Audience :: Science/Research
Classifier: Topic :: Scientific/Engineering :: Bio-Informatics
Requires-Python: >=3.6
Requires-Dist: setuptools (>=56.0.0)
Requires-Dist: pandas (>=1.1.5)
Requires-Dist: numpy (>=1.19.5)
Requires-Dist: statsmodels (>=0.12.2)
Requires-Dist: scipy (>=1.5.4)
Requires-Dist: matplotlib (==3.3.4)
Requires-Dist: joblib (>=1.0.1)
Requires-Dist: scikit-learn (>=0.24.2)
Requires-Dist: tqdm (>=4.62.3)
Requires-Dist: openpyxl (>=3.0.9)
Requires-Dist: graphviz (>=0.18.2)
Requires-Dist: PySimpleGUI (~=4.55.1)
Requires-Dist: pytest (~=6.2.5)
